biberplus/__init__.py
biberplus/reducer/__init__.py
biberplus/reducer/factor_reducer.py
biberplus/reducer/pca_reducer.py
biberplus/reducer/text_encoder.py
biberplus/tagger/__init__.py
biberplus/tagger/biber_plus_tagger.py
biberplus/tagger/biber_run_order.py
biberplus/tagger/config.yaml
biberplus/tagger/constants.py
biberplus/tagger/data_io.py
biberplus/tagger/function_words_tagger.py
biberplus/tagger/tag_frequencies.py
biberplus/tagger/tag_helper.py
biberplus/tagger/tagger.py
biberplus/tagger/tagger_utils.py
biberplus/tagger/constants/amplifiers.txt
biberplus/tagger/constants/analytic_negation.txt
biberplus/tagger/constants/ask_tell.txt
biberplus/tagger/constants/be.txt
biberplus/tagger/constants/concessive_adverbial_subordinators.txt
biberplus/tagger/constants/conditional_adverbial_subordinators.txt
biberplus/tagger/constants/conjucts.txt
biberplus/tagger/constants/demonstrative_pronouns.txt
biberplus/tagger/constants/demonstratives.txt
biberplus/tagger/constants/direct_wh_questions.txt
biberplus/tagger/constants/discourse_particles.txt
biberplus/tagger/constants/do.txt
biberplus/tagger/constants/downtoners.txt
biberplus/tagger/constants/emphatics.txt
biberplus/tagger/constants/first_person_pronouns.txt
biberplus/tagger/constants/function_words.txt
biberplus/tagger/constants/have.txt
biberplus/tagger/constants/hedges.txt
biberplus/tagger/constants/indefinite_pronouns.txt
biberplus/tagger/constants/laughter_acronyms.txt
biberplus/tagger/constants/necessity_modals.txt
biberplus/tagger/constants/nominalizations_stop_list.txt
biberplus/tagger/constants/non_nominalizations.txt
biberplus/tagger/constants/other_adverbial_subordinators.txt
biberplus/tagger/constants/place_adverbials.txt
biberplus/tagger/constants/possibility_modals.txt
biberplus/tagger/constants/predictive_modals.txt
biberplus/tagger/constants/prepositional_phrases.txt
biberplus/tagger/constants/private_verbs.txt
biberplus/tagger/constants/pronoun_it.txt
biberplus/tagger/constants/public_verbs.txt
biberplus-0.4.0.dist-info/LICENSE
biberplus-0.4.0.dist-info/METADATA
biberplus-0.4.0.dist-info/WHEEL
biberplus-0.4.0.dist-info/top_level.txt
biberplus-0.4.0.dist-info/RECORD
