Metadata-Version: 2.2
Name: biberplus
Version: 0.4.0
Summary: A pure Python implementation of Biber's (1988) Variation across Speech and Writing linguistic tags with additional features
Home-page: https://github.com/davidjurgens/biberplus
Author: Kenan Alkiek, David Jurgens
Author-email: kalkiek@umich.edu
License: MIT License
Classifier: Development Status :: 3 - Alpha
Classifier: Intended Audience :: Science/Research
Classifier: License :: OSI Approved :: MIT License
Classifier: Programming Language :: Python :: 3
Requires-Python: >=3.7
License-File: LICENSE
Requires-Dist: pandas
Requires-Dist: numpy
Requires-Dist: spacy>=3.0.0
Requires-Dist: tqdm
Requires-Dist: blis
Requires-Dist: confection
Requires-Dist: PyYAML
Requires-Dist: factor_analyzer
Requires-Dist: matplotlib
Requires-Dist: seaborn
Dynamic: author
Dynamic: author-email
Dynamic: classifier
Dynamic: home-page
Dynamic: license
Dynamic: requires-dist
Dynamic: requires-python
Dynamic: summary
